django_transitions/__init__.py
django_transitions/admin.py
django_transitions/models.py
django_transitions/workflow.py
django_transitions/templates/transitions/change_form.html
django_transitions/templates/transitions/read_only_change_form.html
testapp/migrations/0001_initial.py
testapp/migrations/__init__.py
testapp/tests/__init__.py
testapp/tests/test_admin.py
testapp/tests/test_workflow.py
django_transitions-0.1.dist-info/LICENSE
django_transitions-0.1.dist-info/METADATA
django_transitions-0.1.dist-info/WHEEL
django_transitions-0.1.dist-info/entry_points.txt
django_transitions-0.1.dist-info/top_level.txt
django_transitions-0.1.dist-info/RECORD
