Metadata-Version: 2.1
Name: django-transitions
Version: 0.1
Summary: Integrate pytransitions with Django.
Home-page: https://github.com/PrimarySite/django-transitions
Author: Christian Ledermann
Author-email: christian.ledermann@gmail.com
License: BSD
Keywords: django permission restframework
Platform: UNKNOWN
Classifier: Framework :: Django
Classifier: Framework :: Django :: 1.11
Classifier: Framework :: Django :: 2.0
Classifier: Framework :: Django :: 2.1
Classifier: Programming Language :: Python :: 2
Classifier: Programming Language :: Python :: 2.7
Classifier: Programming Language :: Python :: 3
Classifier: Programming Language :: Python :: 3.4
Classifier: Programming Language :: Python :: 3.5
Classifier: Programming Language :: Python :: 3.6
Classifier: Development Status :: 3 - Alpha
Classifier: License :: OSI Approved :: BSD License
Requires-Dist: Django
Requires-Dist: transitions
